homework/counters/counter_to_27/counter.sv
module counter_bit(
  input clock,
  input reset,
  input adder_a,

  input  counter_bit_carry_in,
  output counter_bit_carry_out,

  output ff_out
  );

  reg adder_to_ff;
  reg ff_to_adder;
  
  // This is the first XOR in a full adder, should go into 
  // the second XOR and the first AND
  wire xor1;
  assign xor1 = adder_a ^ ff_to_adder;

  // Second XOR should go into the flipflop
  assign adder_to_ff = xor1 ^ counter_bit_carry_in;

  // First AND takes the first XOR and the carry in
  wire and1;
  assign and1 = counter_bit_carry_in & xor1;

  // Second AND is takes adder_a and flipflop output
  wire and2;
  assign and2 = adder_a & ff_to_adder;

  // Just ORs the two ANDs and sends them to carry_out
  assign counter_bit_carry_out = and1 | and2;


always @(posedge clock or posedge reset)
begin
  if (reset)
    ff_to_adder <= 1'b0;
  else
    ff_to_adder <= adder_to_ff;
end

  assign ff_out = ff_to_adder;
endmodule

module counter(
  input clock,
  input reset,

  output bit_1,
  output bit_2,
  output bit_3,
  output bit_4,
  output bit_5

);

  wire to_cb_2;
  counter_bit first_cb(
    .clock(clock),
    .reset(reset),

    .adder_a(1'b1),
    .counter_bit_carry_in(1'b0),
    .counter_bit_carry_out(to_cb_2),
    .ff_out(bit_1)
  );
  

  wire to_cb_3;
  counter_bit second_cb(
    .clock(clock),
    .reset(reset),

    .adder_a(1'b0),
    .counter_bit_carry_in(to_cb_2),
    .counter_bit_carry_out(to_cb_3),
    .ff_out(bit_2)
  );

  wire to_cb_4;
  counter_bit third_cb(
    .clock(clock),
    .reset(reset),

    .adder_a(1'b0),
    .counter_bit_carry_in(to_cb_3),
    .counter_bit_carry_out(to_cb_4),
    .ff_out(bit_3)
    );

  wire to_cb_5;
  counter_bit forth_cb(
    .clock(clock),
    .reset(reset),

    .adder_a(1'b0),
    .counter_bit_carry_in(to_cb_4),
    .counter_bit_carry_out(to_cb_5),
    .ff_out(bit_4)
  );

  // wire to_cb_6;
  counter_bit fifth_cb(
    .clock(clock),
    .reset(reset),

    .adder_a(1'b0),
    .counter_bit_carry_in(to_cb_5),
    .counter_bit_carry_out(to_cb_6),
    .ff_out(bit_5)
  );
endmodule

homework/counters/counter_to_27/tb_counter.sv
module testbench();

  reg clk;
  reg res; 

  wire bit_1;
  wire bit_2;
  wire bit_3;
  wire bit_4;
  wire bit_5;

  counter my_counter(
    .clock(clk),
    .reset(res),

    .bit_1(bit_1),
    .bit_2(bit_2),
    .bit_3(bit_3),
    .bit_4(bit_4),
    .bit_5(bit_5)
    );

  always #5 clk = ~clk;

  always @(*) 
    // reset when counter reaches 27 aka 11011
  begin
    if (bit_1 && bit_2 && bit_4 && bit_5)
      res = 1'b1;
      #10
      res = 1'b0;
  end

    
  // always #2 data_in = ~data_in;

  initial begin 
    $dumpfile("dump.vcd");
    $dumpvars(1);

    res = 1'b1;
    clk = 1'b0;

    // data_in = 1'b1;
    #15
    res = 1'b0;


    #400
    $finish();

  end
endmodule

homework/counters/counter_to_27/dump.vcd
$date
	Fri Oct 31 01:09:09 2025
$end
$version
	Icarus Verilog
$end
$timescale
	1s
$end
$scope module testbench $end
$var wire 1 ! bit_5 $end
$var wire 1 " bit_4 $end
$var wire 1 # bit_3 $end
$var wire 1 $ bit_2 $end
$var wire 1 % bit_1 $end
$var reg 1 & clk $end
$var reg 1 ' res $end
$upscope $end
$enddefinitions $end
$comment Show the parameter values. $end
$dumpall
$end
#0
$dumpvars
1'
0&
0%
0$
0#
0"
0!
$end
#5
1&
#10
0&
0'
#15
1%
1&
#20
0&
#25
1$
0%
1&
#30
0&
#35
1%
1&
#40
0&
#45
1#
0$
0%
1&
#50
0&
#55
1%
1&
#60
0&
#65
1$
0%
1&
#70
0&
#75
1%
1&
#80
0&
#85
1"
0#
0$
0%
1&
#90
0&
#95
1%
1&
#100
0&
#105
1$
0%
1&
#110
0&
#115
1%
1&
#120
0&
#125
1#
0$
0%
1&
#130
0&
#135
1%
1&
#140
0&
#145
1$
0%
1&
#150
0&
#155
1%
1&
#160
0&
#165
1!
0"
0#
0$
0%
1&
#170
0&
#175
1%
1&
#180
0&
#185
1$
0%
1&
#190
0&
#195
1%
1&
#200
0&
#205
1#
0$
0%
1&
#210
0&
#215
1%
1&
#220
0&
#225
1$
0%
1&
#230
0&
#235
1%
1&
#240
0&
#245
1"
0#
0$
0%
1&
#250
0&
#255
1%
1&
#260
0&
#265
1$
0%
1&
#270
0&
#275
0!
0"
0$
1'
0%
1&
#280
0&
#285
1%
1&
0'
#290
0&
#295
1$
0%
1&
#300
0&
#305
1%
1&
#310
0&
#315
1#
0$
0%
1&
#320
0&
#325
1%
1&
#330
0&
#335
1$
0%
1&
#340
0&
#345
1%
1&
#350
0&
#355
1"
0#
0$
0%
1&
#360
0&
#365
1%
1&
#370
0&
#375
1$
0%
1&
#380
0&
#385
1%
1&
#390
0&
#395
1#
0$
0%
1&
#400
0&
#405
1%
1&
#410
0&
#415
1$
0%
1&
