lib/d_flipflop.sv
module d_flipflop #(parameter WIDTH = 1) (
  input wire clock,
  input wire reset,
  input wire data_in,
  output reg data_out
);

always @(posedge clock or posedge reset)
begin
  if (reset)
    data_out <= 1'b0;
  else
    data_out <= data_in;
end

endmodule

lib/full_adder.sv
// `include "8_gates.sv"
module full_adder #(parameter WIDTH = 1) (
  input [WIDTH-1:0] full_adder_a,
  input [WIDTH-1:0] full_adder_b,
  input [WIDTH-1:0] full_adder_carry_in,

  output [WIDTH-1:0] full_adder_sum,
  output [WIDTH-1:0] full_adder_carry_out
);
  wire xor1;

  xor_gate xor_a_b (
    .xor_a(full_adder_a),
    .xor_b(full_adder_b),
    .xor_out(xor1)
  );

  xor_gate xor_xor1_carryin (
    .xor_a(xor1),
    .xor_b(full_adder_carry_in),
    .xor_out(full_adder_sum)
  );

  wire and1;
  and_gate and_carryin_xor1 (
    .and_a(full_adder_carry_in),
    .and_b(xor1),
    .and_out(and1)
  );

  wire and2;
  and_gate and_a_b (
    .and_a(full_adder_a),
    .and_b(full_adder_b),
    .and_out(and2)
  );

  or_gate or_and1_and2(
    .or_a(and1),
    .or_b(and2),
    .or_out(full_adder_carry_out)
  );
endmodule

homework/counters/4bit_counter/counter.sv
module counter_bit(
  input clock,
  input reset,
  input adder_a,

  input  counter_bit_carry_in,
  output counter_bit_carry_out,
  
  output reg ff_out
  );

  //
  wire adder_to_ff;
  wire ff_to_adder;

  full_adder full_adder(
    .full_adder_a(adder_a),
    .full_adder_b(ff_to_adder),
    .full_adder_carry_in(counter_bit_carry_in),

    .full_adder_sum(adder_to_ff),
    .full_adder_carry_out(counter_bit_carry_out)
    );

  d_flipflop d_ff(
    .clock(clock),
    .reset(reset),

    .data_in(adder_to_ff),
    .data_out(ff_to_adder)
    );

  assign ff_out = ff_to_adder;
endmodule


module counter(
  input clock,
  input reset,

  output bit_1,
  output bit_2,
  output bit_3,
  output bit_4
);
  wire to_cb_2;
  counter_bit first_cb(
    .clock(clock),
    .reset(reset),

    .adder_a(1'b1),
    .counter_bit_carry_in(1'b0),
    .counter_bit_carry_out(to_cb_2),
    .ff_out(bit_1)
  );
  

  wire to_cb_3;
  counter_bit second_cb(
    .clock(clock),
    .reset(reset),

    .adder_a(1'b0),
    .counter_bit_carry_in(to_cb_2),
    .counter_bit_carry_out(to_cb_3),
    .ff_out(bit_2)
  );

  wire to_cb_4;
  counter_bit third_cb(
    .clock(clock),
    .reset(reset),

    .adder_a(1'b0),
    .counter_bit_carry_in(to_cb_3),
    .counter_bit_carry_out(to_cb_4),
    .ff_out(bit_3)
    );

  // wire to_cb_5;
  counter_bit forth_cb(
    .clock(clock),
    .reset(reset),

    .adder_a(1'b0),
    .counter_bit_carry_in(to_cb_4),
    .counter_bit_carry_out(to_cb_5),
    .ff_out(bit_4)
  );

endmodule

  // //
  // wire 2_adder_to_2_ff;
  // wire 2_ff_to_2_adder;
  // wire 2_adder_to_3_adder;
  //
  // full_adder 2nd_fa(
  //   .full_adder_a(1'b0),
  //   .full_adder_b(2_ff_to_2_adder),
  //   .full_adder_carry_in(1_adder_to_2_adder),
  //
  //   .full_adder_sum(1_adder_to_2adder),
  //   .full_adder_carry_out(2_adder_to_3_adder)
  //   );
  //
  // d_ff 2nd_d_ff(
  //   .clk(clock),
  //   .res(reset),
  //   .data_in(2_adder_to_2_ff),
  //   .data_out(2_ff_to_2_adder)
  //   );
  //
  //   //
  // wire 3_adder_to_3_ff;
  // wire 3_ff_to_3_adder;
  // wire 3_adder_to_4_adder;
  //
  // full_adder 3rd_fa(
  //   .full_adder_a(1'b0),
  //   .full_adder_b(3_ff_to_3_adder),
  //   .full_adder_carry_in(2_adder_to_3_adder),
  //
  //   .full_adder_sum(3_adder_to_3adder),
  //   .full_adder_carry_out(3_adder_to_4_adder)
  //   );
  //
  // d_ff 2nd_d_ff(
  //   .clk(clock),
  //   .res(reset),
  //   .data_in(3_adder_to_3_ff),
  //   .data_out(3_ff_to_3_adder)
  //   );
  //
  //
  // //
  // wire 4_adder_to_4_ff;
  // wire 4_ff_to_4_adder;
  //
  // full_adder 3rd_fa(
  //   .full_adder_a(1'b0),
  //   .full_adder_b(4_ff_to_4_adder),
  //   .full_adder_carry_in(3_adder_to_4_adder),
  //
  //   .full_adder_sum(4_adder_to_4_ff),
  //   .full_adder_carry_out()
  //   );
  //
  // d_ff 2nd_d_ff(
  //   .clk(clock),
  //   .res(reset),
  //   .data_in(4_adder_to_4_ff),
  //
  //   .data_out(4_ff_to_4_adder)
  //   );

// endmodule

homework/counters/4bit_counter/counter_tb.sv
module testbench();

  reg clk;
  reg res; 

  wire bit_1;
  wire bit_2;
  wire bit_3;
  wire bit_4;

  counter my_counter(
    .clock(clk),
    .reset(res),

    .bit_1(bit_1),
    .bit_2(bit_2),
    .bit_3(bit_3),
    .bit_4(bit_4)
    );

  always #5 clk = ~clk;

  // always @(*) 
  //   // reset when counter reaches 27 aka 11011
  // begin
  //   if (bit_1 && bit_2 && bit_4 && bit_5)
  //     res = 1'b1;
  //     #10
  //     res = 1'b0;
  // end

    
  // always #2 data_in = ~data_in;

  initial begin 
    $dumpfile("dump.vcd");
    $dumpvars(1);

    res = 1'b1;
    clk = 1'b0;

    // data_in = 1'b1;
    #15
    res = 1'b0;


    #400
    $finish();

  end
endmodule

homework/6-bit_counter/8_gates.sv
// 1: AND (only if both)
module and_gate (
    input and_a,
    input and_b,

    output and_out
);

  assign and_out = and_a && and_b;
endmodule

// 2: OR (if either)
module or_gate (
    input or_a,
    input or_b,

    output or_out
);

  assign or_out = or_a || or_b;
endmodule

// 3: NOT (inverts the input
module not_gate (
    input not_a,

    output not_out
);

  assign not_out = !not_a;
endmodule

// 4: NAND (if both then off, on otherwise)
module nand_gate (
    input nand_a,
    input nand_b,

    output nand_out
);

  assign nand_out = !(nand_a && nand_b);
endmodule

// 5: NOR (only if both off)
module nor_gate (
    input nor_a,
    input nor_b,

    output nor_out
);

  assign nor_out = !(nor_a || nor_b);
endmodule

// 6: XOR (either one, but not both)
module xor_gate (
    input xor_a,
    input xor_b,

    output xor_out
);

  assign xor_out = (xor_a || xor_b) && !(xor_a && xor_b);
endmodule

// 7: XNOR (either both on, or both off)
module xnor_gate (
    input xnor_a,
    input xnor_b,

    output xnor_out
);

  assign xnor_out = !((xnor_a || xnor_b) && !(xnor_a && xnor_b));
endmodule

// 8: BUFFER (returns the inputs)
module buff_gate (
    input buff_a,

    output buff_out
);

  assign buff_out = buff_a;
endmodule

homework/counters/4bit_counter/dump.vcd
$date
	Fri Oct 31 01:09:40 2025
$end
$version
	Icarus Verilog
$end
$timescale
	1s
$end
$scope module buff_gate $end
$var wire 1 ! buff_a $end
$var wire 1 " buff_out $end
$upscope $end
$scope module nand_gate $end
$var wire 1 # nand_a $end
$var wire 1 $ nand_b $end
$var wire 1 % nand_out $end
$upscope $end
$scope module nor_gate $end
$var wire 1 & nor_a $end
$var wire 1 ' nor_b $end
$var wire 1 ( nor_out $end
$upscope $end
$scope module not_gate $end
$var wire 1 ) not_a $end
$var wire 1 * not_out $end
$upscope $end
$scope module testbench $end
$var wire 1 + bit_4 $end
$var wire 1 , bit_3 $end
$var wire 1 - bit_2 $end
$var wire 1 . bit_1 $end
$var reg 1 / clk $end
$var reg 1 0 res $end
$upscope $end
$scope module xnor_gate $end
$var wire 1 1 xnor_a $end
$var wire 1 2 xnor_b $end
$var wire 1 3 xnor_out $end
$upscope $end
$enddefinitions $end
$comment Show the parameter values. $end
$dumpall
$end
#0
$dumpvars
x3
z2
z1
10
0/
0.
0-
0,
0+
x*
z)
x(
z'
z&
x%
z$
z#
z"
z!
$end
#5
1/
#10
0/
#15
1.
1/
00
#20
0/
#25
1-
0.
1/
#30
0/
#35
1.
1/
#40
0/
#45
1,
0-
0.
1/
#50
0/
#55
1.
1/
#60
0/
#65
1-
0.
1/
#70
0/
#75
1.
1/
#80
0/
#85
1+
0,
0-
0.
1/
#90
0/
#95
1.
1/
#100
0/
#105
1-
0.
1/
#110
0/
#115
1.
1/
#120
0/
#125
1,
0-
0.
1/
#130
0/
#135
1.
1/
#140
0/
#145
1-
0.
1/
#150
0/
#155
1.
1/
#160
0/
#165
0+
0,
0-
0.
1/
#170
0/
#175
1.
1/
#180
0/
#185
1-
0.
1/
#190
0/
#195
1.
1/
#200
0/
#205
1,
0-
0.
1/
#210
0/
#215
1.
1/
#220
0/
#225
1-
0.
1/
#230
0/
#235
1.
1/
#240
0/
#245
1+
0,
0-
0.
1/
#250
0/
#255
1.
1/
#260
0/
#265
1-
0.
1/
#270
0/
#275
1.
1/
#280
0/
#285
1,
0-
0.
1/
#290
0/
#295
1.
1/
#300
0/
#305
1-
0.
1/
#310
0/
#315
1.
1/
#320
0/
#325
0+
0,
0-
0.
1/
#330
0/
#335
1.
1/
#340
0/
#345
1-
0.
1/
#350
0/
#355
1.
1/
#360
0/
#365
1,
0-
0.
1/
#370
0/
#375
1.
1/
#380
0/
#385
1-
0.
1/
#390
0/
#395
1.
1/
#400
0/
#405
1+
0,
0-
0.
1/
#410
0/
#415
1.
1/
